textualicious/__init__.py
textualicious/dataclass_table.py
textualicious/dataclass_viewer.py
textualicious/functional.py
textualicious/help_screen.py
textualicious/icon_widget.py
textualicious/log_widget/__init__.py
textualicious/log_widget/log_widget.py
textualicious/log_widget/widget_handler.py
textualicious/logwidget.py
textualicious/py.typed
textualicious/upath_tree.py
textualicious/utils.py
textualicious-1.0.0.dist-info/WHEEL
textualicious-1.0.0.dist-info/METADATA
textualicious-1.0.0.dist-info/RECORD
