Metadata-Version: 2.3
Name: textualicious
Version: 1.0.0
Summary: Textual widgets and integrations
Keywords: 
Author: Philipp Temminghoff
Author-email: Philipp Temminghoff <philipptemminghoff@googlemail.com>
License: MIT License
Classifier: Development Status :: 4 - Beta
Classifier: Intended Audience :: Developers
Classifier: Operating System :: OS Independent
Classifier: Programming Language :: Python :: 3
Classifier: Programming Language :: Python :: 3 :: Only
Classifier: Programming Language :: Python :: 3.12
Classifier: Programming Language :: Python :: 3.13
Classifier: Programming Language :: Python :: 3.14
Classifier: Topic :: Documentation
Classifier: Topic :: Software Development
Classifier: Topic :: Utilities
Classifier: Typing :: Typed
Requires-Dist: fieldz>=0.1.0
Requires-Dist: textual>=1.0.0
Requires-Python: >=3.13
Project-URL: Code coverage, https://app.codecov.io/gh/phil65/textualicious
Project-URL: Discussions, https://github.com/phil65/textualicious/discussions
Project-URL: Documentation, https://phil65.github.io/textualicious/
Project-URL: Issues, https://github.com/phil65/textualicious/issues
Project-URL: Source, https://github.com/phil65/textualicious
